{
  "tasks": [
    {
      "id": "9e540bb6-deff-4a56-88e0-568cb1321912",
      "title": "Teste",
      "time": "morning",
      "description": "teste",
      "status": "not_started"
    },
    {
      "id": "6eed7ef3-e4d5-4e97-bc0c-df62a090bc6c",
      "title": "Teste",
      "time": "evening",
      "description": "Teste",
      "status": "not_started"
    },
    {
      "id": "f1cd0238-a650-4021-8eac-fb2d8cb0926a",
      "title": "Estudar",
      "time": "afternoon",
      "description": "Estudar react js",
      "status": "not_started"
    }
  ]
}